finalsa/sqs/consumer/__init__.py
finalsa/sqs/consumer/app/__init__.py
finalsa/sqs/consumer/app/app.py
finalsa/sqs/consumer/app/base_model_attr.py
finalsa/sqs/consumer/app/build_sqs_depends.py
finalsa/sqs/consumer/app/consumer.py
finalsa/sqs/consumer/app/dict_model_attr.py
finalsa/sqs/consumer/app/exceptions.py
finalsa/sqs/consumer/app/executor.py
finalsa/sqs/consumer/app/get_function_attrs.py
finalsa/sqs/consumer/app/get_missing_attrs.py
finalsa/sqs/consumer/app/interceptors.py
finalsa/sqs/consumer/app/signal_handler.py
finalsa/sqs/consumer/app/sqs_depends.py
finalsa/sqs/consumer/testing/__init__.py
finalsa/sqs/consumer/testing/app.py
finalsa_sqs_consumer-3.0.5.dist-info/METADATA
finalsa_sqs_consumer-3.0.5.dist-info/WHEEL
finalsa_sqs_consumer-3.0.5.dist-info/licenses/LICENSE.md
finalsa_sqs_consumer-3.0.5.dist-info/RECORD
