Metadata-Version: 2.4
Name: finalsa-sqs-consumer
Version: 3.0.5
Summary: High-performance SQS message consumer with worker-based concurrency, dependency injection, and async support for Python applications
Project-URL: Homepage, https://github.com/finalsa/finalsa-sqs-consumer
Author-email: Luis Jimenez <luis@finalsa.com>
License: MIT License
License-File: LICENSE.md
Keywords: async,aws,concurrency,consumer,dependency-injection,fastapi,finalsa,interceptors,message-queue,sqs,timeout,worker
Requires-Python: >=3.10
Requires-Dist: finalsa-common-models>=2.0.3
Requires-Dist: finalsa-dependency-injector>=0.1.5
Requires-Dist: finalsa-sns-client>=2.2.1
Requires-Dist: finalsa-sqs-client>=2.1.1
Requires-Dist: finalsa-traceability>=1.0.1
Requires-Dist: orjson>=3.11.2
